{
  "status": "success",
  "title": "Alpha158-KLOW2",
  "title_hash": "e78502211b65717afd9de7080cc8653ed681979a3ec244bc8bae49df4eea3463",
  "formula_hash": "578afb5615013e65ff9cdf141c6d357f3ddd480a2256605d915b636ba2b877a4",
  "expression_version": "1",
  "engine_version": "0.1.0",
  "metrics_version": "0.1.0",
  "evaluation_type": "cross_sectional",
  "evaluated_at": "2026-06-30T02:16:43.036380+00:00",
  "data_range": {
    "start": "2023-01-01",
    "end": "2026-05-31",
    "n_bars": 6569119
  },
  "factor_sql": {
    "version": "1",
    "dialect": "duckdb-factor-v1",
    "evaluation_type": "cross_sectional",
    "data_source": "yhydev97/quant-data",
    "signal_sql": "(LEAST(open, close) - low) / (high - low + 1e-12)",
    "postprocess": "cs_rank",
    "universe": {
      "dropna": [
        "open",
        "high",
        "low",
        "close"
      ],
      "min_symbol_bars": 168,
      "cs_quantile_gte": {
        "col": "quote_volume",
        "q": 0.2
      }
    }
  },
  "metrics": {
    "mean_ic": -0.006084060864419309,
    "ic_ir": -0.06269783471171415,
    "mean_rank_ic": -0.007188340896273624,
    "rank_ic_ir": -0.07016435952345806,
    "n_periods": 29925,
    "ic_positive_ratio": 0.4694736842105263
  },
  "diagnostics": {
    "skipped_periods_low_n": 1,
    "avg_universe_size": 219.48731914324858
  }
}
